CHANGES.rst
LICENSE.GPL
LICENSE.rst
MANIFEST.in
README.rst
setup.cfg
setup.py
src/collective/__init__.py
src/collective.easyformplugin.fields.egg-info/PKG-INFO
src/collective.easyformplugin.fields.egg-info/SOURCES.txt
src/collective.easyformplugin.fields.egg-info/dependency_links.txt
src/collective.easyformplugin.fields.egg-info/entry_points.txt
src/collective.easyformplugin.fields.egg-info/namespace_packages.txt
src/collective.easyformplugin.fields.egg-info/not-zip-safe
src/collective.easyformplugin.fields.egg-info/requires.txt
src/collective.easyformplugin.fields.egg-info/top_level.txt
src/collective/easyformplugin/__init__.py
src/collective/easyformplugin/fields/__init__.py
src/collective/easyformplugin/fields/configure.zcml
src/collective/easyformplugin/fields/consent_display.pt
src/collective/easyformplugin/fields/consent_input.pt
src/collective/easyformplugin/fields/divider.pt
src/collective/easyformplugin/fields/fields.py
src/collective/easyformplugin/fields/interfaces.py
src/collective/easyformplugin/fields/setuphandlers.py
src/collective/easyformplugin/fields/view.py
src/collective/easyformplugin/fields/widgets.py
src/collective/easyformplugin/fields/widgets.zcml
src/collective/easyformplugin/fields/locales/README.rst
src/collective/easyformplugin/fields/locales/__init__.py
src/collective/easyformplugin/fields/locales/collective.easyformplugin.fields.pot
src/collective/easyformplugin/fields/locales/update.py
src/collective/easyformplugin/fields/locales/update.sh
src/collective/easyformplugin/fields/locales/de/LC_MESSAGES/collective.easyformplugin.fields.po
src/collective/easyformplugin/fields/locales/en/LC_MESSAGES/collective.easyformplugin.fields.po
src/collective/easyformplugin/fields/profiles/default/browserlayer.xml
src/collective/easyformplugin/fields/profiles/default/metadata.xml
src/collective/easyformplugin/fields/profiles/default/registry.xml
src/collective/easyformplugin/fields/profiles/uninstall/browserlayer.xml
src/collective/easyformplugin/fields/resources/styles.css