Metadata-Version: 2.1
Name: collective.easyformplugin.fields
Version: 1.0
Summary: Extra fields for easyform
Home-page: https://github.com/collective/collective.easyformplugin.fields
Author: Johannes Raggam
Author-email: thetetet@gmail.com
License: GPL version 2
Project-URL: PyPI, https://pypi.python.org/pypi/collective.easyformplugin.fields
Project-URL: Source, https://github.com/collective/collective.easyformplugin.fields
Project-URL: Tracker, https://github.com/collective/collective.easyformplugin.fields/issues
Keywords: Python Plone
Platform: UNKNOWN
Classifier: Development Status :: 5 - Production/Stable
Classifier: Environment :: Web Environment
Classifier: Framework :: Plone
Classifier: Framework :: Plone :: Addon
Classifier: Framework :: Plone :: 5.2
Classifier: Programming Language :: Python
Classifier: Programming Language :: Python :: 2.7
Classifier: Programming Language :: Python :: 3.6
Classifier: Programming Language :: Python :: 3.7
Classifier: Operating System :: OS Independent
Classifier: License :: OSI Approved :: GNU General Public License v2 (GPLv2)
Requires-Python: >=2.7
Provides-Extra: test
License-File: LICENSE.GPL
License-File: LICENSE.rst
